[{"Carnet":"u20098471","Nombres":"Christian Eduardo","Apellidos":"Silva Palma","Carrera":"Ing Agronomica","Nota_1":"7.00","Nota_2":"9.00","Nota_3":"10.00"},{"Carnet":"u20120168","Nombres":"Oscar Fernando","Apellidos":"Ventura Ortiz","Carrera":"Ing En Sistemas","Nota_1":"10.00","Nota_2":"9.00","Nota_3":"10.00"},{"Carnet":"u20129085","Nombres":"Marco Tulio","Apellidos":"Argueta Chicas","Carrera":"Ing en Sistemas","Nota_1":"8.00","Nota_2":"9.00","Nota_3":"10.00"},{"Carnet":"u20129847","Nombres":"Maritzabel ","Apellidos":"Castillo Ramos","Carrera":"Lic en Ciencias Juridicas","Nota_1":"10.00","Nota_2":"9.40","Nota_3":"10.00"},{"Carnet":"u20158903","Nombres":"Jenny Patricia","Apellidos":"Perez Mendoza","Carrera":"Lic en Admon de Empresas","Nota_1":"10.00","Nota_2":"9.00","Nota_3":"8.00"}]